kcwmysql
